eiptek3api/__init__.py
eiptek3api/__main__.py
eiptek3api/api.py
eiptek3api/filter.py
eiptek3api/stats.py
eiptek3api-0.0.7.dist-info/METADATA
eiptek3api-0.0.7.dist-info/WHEEL
eiptek3api-0.0.7.dist-info/entry_points.txt
eiptek3api-0.0.7.dist-info/licenses/LICENSE
eiptek3api-0.0.7.dist-info/RECORD
