Metadata-Version: 2.3
Name: eiptek3api
Version: 0.0.7
Summary: Small python package for https://eip-tek3.epitest.eu api
Project-URL: Homepage, https://gitea.saverio976.ovh/Saverio976/eiptek3-api
Project-URL: Issues, https://gitea.saverio976.ovh/Saverio976/eiptek3-api/issues
Author-email: Xavier Mitault <xavier.mitault@epitech.eu>
License-File: LICENSE
Classifier: License :: OSI Approved :: MIT License
Classifier: Operating System :: OS Independent
Classifier: Programming Language :: Python :: 3
Requires-Python: >=3.10
Requires-Dist: python-dateutil
Requires-Dist: requests
